benchmark.cpython-39-aarch64-linux-gnu.so
plant_care.cpython-39-aarch64-linux-gnu.so
wyr/__init__.py
wyr/atom.c
wyr/atom.cpython-39-aarch64-linux-gnu.so
wyr/atom_diff.c
wyr/atom_diff.cpython-39-aarch64-linux-gnu.so
wyr/atom_utils.c
wyr/atom_utils.cpython-39-aarch64-linux-gnu.so
wyr/cli.c
wyr/cli.cpython-39-aarch64-linux-gnu.so
wyr/code_utils.c
wyr/code_utils.cpython-39-aarch64-linux-gnu.so
wyr/configuration.c
wyr/configuration.cpython-39-aarch64-linux-gnu.so
wyr/log.c
wyr/log.cpython-39-aarch64-linux-gnu.so
wyr/metadata_extractor.c
wyr/metadata_extractor.cpython-39-aarch64-linux-gnu.so
wyr/synthetic_data_generator.c
wyr/synthetic_data_generator.cpython-39-aarch64-linux-gnu.so
wyr/template_extractor.c
wyr/template_extractor.cpython-39-aarch64-linux-gnu.so
wyr/trainer.c
wyr/trainer.cpython-39-aarch64-linux-gnu.so
wyr/atom_detectors/base.c
wyr/atom_detectors/base.cpython-39-aarch64-linux-gnu.so
wyr/atom_detectors/ollama_detector.c
wyr/atom_detectors/ollama_detector.cpython-39-aarch64-linux-gnu.so
wyr/atom_detectors/simple_detector.c
wyr/atom_detectors/simple_detector.cpython-39-aarch64-linux-gnu.so
wyr/commands/analyze_semantics.c
wyr/commands/analyze_semantics.cpython-39-aarch64-linux-gnu.so
wyr/commands/criticize.c
wyr/commands/criticize.cpython-39-aarch64-linux-gnu.so
wyr/commands/data.c
wyr/commands/data.cpython-39-aarch64-linux-gnu.so
wyr/commands/detect.c
wyr/commands/detect.cpython-39-aarch64-linux-gnu.so
wyr/commands/extract_metadata.c
wyr/commands/extract_metadata.cpython-39-aarch64-linux-gnu.so
wyr/commands/extract_templates.c
wyr/commands/extract_templates.cpython-39-aarch64-linux-gnu.so
wyr/commands/info.c
wyr/commands/info.cpython-39-aarch64-linux-gnu.so
wyr/commands/init.c
wyr/commands/init.cpython-39-aarch64-linux-gnu.so
wyr/commands/instrument.c
wyr/commands/instrument.cpython-39-aarch64-linux-gnu.so
wyr/commands/label.c
wyr/commands/label.cpython-39-aarch64-linux-gnu.so
wyr/commands/list_atoms.c
wyr-0.1.0.dist-info/METADATA
wyr-0.1.0.dist-info/WHEEL
wyr-0.1.0.dist-info/entry_points.txt
wyr-0.1.0.dist-info/top_level.txt
wyr-0.1.0.dist-info/RECORD
